mcpp/__init__.py
mcpp/__main__.py
mcpp/additional.py
mcpp/complexity.py
mcpp/config.py
mcpp/memory.py
mcpp/parse.py
mcpp/queries.py
mcpp/smell.py
mcpp/tree.py
mcpp/vulnerability.py
mcpp/assets/__init__.py
mcpp/assets/config.yaml
mcpp-1.3.2.dist-info/licenses/LICENSE
mcpp-1.3.2.dist-info/METADATA
mcpp-1.3.2.dist-info/WHEEL
mcpp-1.3.2.dist-info/entry_points.txt
mcpp-1.3.2.dist-info/top_level.txt
mcpp-1.3.2.dist-info/RECORD
