Metadata-Version: 2.4
Name: mcpp
Version: 1.3.2
Summary: McCabe++ (mcpp): cyclomatic complexity and other vulnerability-related code metrics
Author-email: Lukas Pirch <lukas.pirch@tu-berlin.de>
License: MIT License
Keywords: vulnerability,code metric,static analysis
Classifier: Programming Language :: Python
Classifier: Programming Language :: Python :: 3
Requires-Python: <3.14,>=3.9
License-File: LICENSE
Requires-Dist: hydra-core>=1.3.2
Requires-Dist: tree-sitter>=0.24.0
Requires-Dist: tree-sitter-c>=0.23.0
Requires-Dist: tree-sitter-cpp>=0.23.0
Requires-Dist: tqdm>=4.66.0
Requires-Dist: loguru>=0.7.0
Dynamic: license-file
